pypdfserver/__init__.py
pypdfserver/__main__.py
pypdfserver/cmd.py
pypdfserver/core.py
pypdfserver/default.ini
pypdfserver/default_profiles.ini
pypdfserver/html.py
pypdfserver/log.py
pypdfserver/pdf_worker.py
pypdfserver/server.py
pypdfserver/settings.py
pypdfserver/html/index.html
pypdfserver-1.1.2.dist-info/METADATA
pypdfserver-1.1.2.dist-info/WHEEL
pypdfserver-1.1.2.dist-info/licenses/LICENSE
pypdfserver-1.1.2.dist-info/RECORD
