Metadata-Version: 2.4
Name: pyPDFServer
Version: 1.1.2
Summary: Host your own local PDF server applying OCR and duplex scanning on your documents
Project-URL: Repository, https://github.com/andreasmz/pypdfserver
Project-URL: Issues, https://github.com/andreasmz/pypdfserver/issues
Author: Andreas Brilka
License-Expression: MIT
License-File: LICENSE
Classifier: Development Status :: 5 - Production/Stable
Classifier: Programming Language :: Python :: 3
Requires-Python: >=3.10
Requires-Dist: flask>=3.1.2
Requires-Dist: ocrmypdf>=16.3
Requires-Dist: platformdirs>=4.5
Requires-Dist: prompt-toolkit>=3.0.52
Requires-Dist: pyftpdlib~=2.1
Requires-Dist: pypdf~=6.5
